LICENSE
MANIFEST.in
README.rst
requirements.txt
setup.cfg
setup.py
ckanext/__init__.py
ckanext/openformat/__init__.py
ckanext/openformat/controllers.py
ckanext/openformat/plugin.py
ckanext/openformat/tests/__init__.py
ckanext/openformat/tests/test_plugin.py
ckanext_openformat.egg-info/PKG-INFO
ckanext_openformat.egg-info/SOURCES.txt
ckanext_openformat.egg-info/dependency_links.txt
ckanext_openformat.egg-info/entry_points.txt
ckanext_openformat.egg-info/namespace_packages.txt
ckanext_openformat.egg-info/top_level.txt