Metadata-Version: 1.1
Name: ckanext-openformat
Version: 0.0.1
Summary: CKAN extension to restrict fupload when uploading resources file
Home-page: https://github.com/ericsnth/ckanext-openformat
Author: Ericson Thomas
Author-email: ericsn.th@gmail.com
License: Apache License 2.0
Keywords: CKAN openformat
Platform: UNKNOWN
Classifier: Development Status :: 5 - Production/Stable
Classifier: Programming Language :: Python
Classifier: Programming Language :: Python :: 2.7
Classifier: Topic :: Software Development :: Libraries
